mamimo/__init__.py
mamimo/analysis.py
mamimo/carryover.py
mamimo/datasets/__init__.py
mamimo/datasets/_load_fake_mmm.py
mamimo/linear_model.py
mamimo/saturation.py
mamimo/time_utils.py
mamimo-0.4.3.dist-info/WHEEL
mamimo-0.4.3.dist-info/METADATA
mamimo-0.4.3.dist-info/RECORD
