Metadata-Version: 2.1
Name: mamimo
Version: 0.4.3
Summary: A package to create marketing mix models.
Home-page: https://github.com/Garve/mamimo
Author: Robert Kübler
Author-email: xgarve@gmail.com
Requires-Python: >=3.9,<4.0
Classifier: Programming Language :: Python :: 3
Classifier: Programming Language :: Python :: 3.10
Classifier: Programming Language :: Python :: 3.9
Requires-Dist: numpy (>=1.22.3,<2.0.0)
Requires-Dist: pandas (>=1.4.2,<2.0.0)
Requires-Dist: scikit-learn (>=1.0.2,<2.0.0)
Project-URL: Repository, https://github.com/Garve/mamimo
